stancemining/__init__.py
stancemining/base.py
stancemining/datasets.py
stancemining/estimate.py
stancemining/finetune.py
stancemining/llms.py
stancemining/main.py
stancemining/metrics.py
stancemining/plot.py
stancemining/prompting.py
stancemining/utils.py
stancemining-0.2.0.dist-info/METADATA
stancemining-0.2.0.dist-info/WHEEL
stancemining-0.2.0.dist-info/licenses/LICENSE
stancemining-0.2.0.dist-info/RECORD
