Metadata-Version: 2.4
Name: stancemining
Version: 0.2.0
Summary: A library for stance detection and target extraction in text data.
License-Expression: MIT
License-File: LICENSE
Requires-Python: >=3.10
Requires-Dist: accelerate>=1.7.0
Requires-Dist: adjusttext>=1.3.0
Requires-Dist: bert-score>=0.3.13
Requires-Dist: cuml-cu12
Requires-Dist: datasets>=3.6.0
Requires-Dist: evaluate>=0.4.3
Requires-Dist: gpytorch>=1.14
Requires-Dist: matplotlib>=3.10.3
Requires-Dist: ninja>=1.11.1.4
Requires-Dist: nltk>=3.9.1
Requires-Dist: numpy
Requires-Dist: packaging>=25.0
Requires-Dist: pandas
Requires-Dist: peft>=0.15.2
Requires-Dist: polars>=1.30.0
Requires-Dist: pyro-ppl>=1.9.1
Requires-Dist: pytest>=8.4.0
Requires-Dist: sacrebleu>=2.5.1
Requires-Dist: scikit-learn>=1.7.0
Requires-Dist: scipy>=1.15.3
Requires-Dist: sentence-transformers>=4.1.0
Requires-Dist: toponymy
Requires-Dist: torch
Requires-Dist: torchvision
Requires-Dist: tqdm>=4.67.1
Requires-Dist: vllm>=0.7.0
Requires-Dist: wandb>=0.20.1
